qfunction/__init__.py
qfunction/base/__init__.py
qfunction/base/base.py
qfunction/base/calculus.py
qfunction/base/trigonometry.py
qfunction/classic_circuit/__init__.py
qfunction/classic_circuit/classic_circuit.py
qfunction/fundamentals/__init__.py
qfunction/fundamentals/calculus.py
qfunction/fundamentals/canonic.py
qfunction/fundamentals/fundamentals.py
qfunction/fundamentals/trigonometry.py
qfunction/plot/__init__.py
qfunction/plot/bloch_sphere.py
qfunction/plot/histogram.py
qfunction/quantum/__init__.py
qfunction/quantum/equations.py
qfunction/quantum/hilbert_vector.py
qfunction/quantum/quantum_circuit.py
qfunction/quantum/simulator.py
qfunction/quantum/algorithms/__init__.py
qfunction/quantum/algorithms/game_arena.py
qfunction-1.0.1642.dist-info/LICENSE
qfunction-1.0.1642.dist-info/METADATA
qfunction-1.0.1642.dist-info/WHEEL
qfunction-1.0.1642.dist-info/top_level.txt
qfunction-1.0.1642.dist-info/RECORD
