Metadata-Version: 2.1
Name: qfunction
Version: 1.0.1642
Summary: Library for researcher with statistics and mechanics equation non-extensive 📈📊📚
Home-page: https://github.com/gpftc/qfunction
Author: Reinan Br
Author-email: slimchatuba@gmail.com
License: MIT License
Keywords: qfunction non-extensive mechanical statistical data science
Platform: UNKNOWN
Requires-Dist: numpy
Requires-Dist: qutip
Requires-Dist: tqdm
Requires-Dist: matplotlib
Requires-Dist: imageio
Requires-Dist: bs4
Requires-Dist: requests
